{
  "last_sync": "2026-04-27T17:50:25.730776",
  "script_status": {
    "xbai02b": {
      "running": true,
      "copies": 3,
      "pids": [
        12740,
        12742,
        12744
      ],
      "last_seen": "2026-04-27T17:50:04.909054",
      "paused": false
    },
    "zwang43b": {
      "running": true,
      "copies": 3,
      "pids": [
        12754,
        12774,
        12780
      ],
      "last_seen": "2026-04-27T17:50:04.909082",
      "paused": false
    }
  },
  "total_copies": 6,
  "users": [
    {
      "name": "xbai02b",
      "status": "RUNNING",
      "instances": 3,
      "paused": false
    },
    {
      "name": "zwang43b",
      "status": "RUNNING",
      "instances": 3,
      "paused": false
    }
  ],
  "reservations": [],
  "bookings": [
    {
      "timestamp": "2026-04-27T06:00:56.713212-04:00",
      "timestamp_display": "2026-04-27 06:00:56.713",
      "user": "xbai02b",
      "service": "bubble",
      "booking_date": "2026-04-29",
      "booking_hour": 17,
      "weekday": "Wednesday",
      "success": false,
      "message": "Unable to find any available Court",
      "error_type": "no_availability",
      "court_id": null,
      "court_number": null,
      "court_index": null,
      "response_time_ms": 531,
      "seconds_after_hour": 56.725,
      "booking_window": "6am",
      "thread_id": 1,
      "phase": "rapid",
      "attempt_number": 4,
      "session_age_seconds": 14.5,
      "copy_id": 3,
      "pid": 734725
    },
    {
      "timestamp": "2026-04-27T06:00:54.399125-04:00",
      "timestamp_display": "2026-04-27 06:00:54.399",
      "user": "xbai02b",
      "service": "bubble",
      "booking_date": "2026-04-29",
      "booking_hour": 14,
      "weekday": "Wednesday",
      "success": false,
      "message": "Unable to find any available Court",
      "error_type": "no_availability",
      "court_id": null,
      "court_number": null,
      "court_index": null,
      "response_time_ms": 506,
      "seconds_after_hour": 56.725,
      "booking_window": "6am",
      "thread_id": 1,
      "phase": "rapid",
      "attempt_number": 3,
      "session_age_seconds": 12.2,
      "copy_id": 3,
      "pid": 734725
    },
    {
      "timestamp": "2026-04-27T06:00:51.898256-04:00",
      "timestamp_display": "2026-04-27 06:00:51.898",
      "user": "xbai02b",
      "service": "bubble",
      "booking_date": "2026-04-29",
      "booking_hour": 17,
      "weekday": "Wednesday",
      "success": false,
      "message": "Unable to find any available Court",
      "error_type": "no_availability",
      "court_id": null,
      "court_number": null,
      "court_index": null,
      "response_time_ms": 348,
      "seconds_after_hour": 56.724,
      "booking_window": "6am",
      "thread_id": 1,
      "phase": "rapid",
      "attempt_number": 2,
      "session_age_seconds": 9.8,
      "copy_id": 3,
      "pid": 734725
    },
    {
      "timestamp": "2026-04-27T06:00:49.910260-04:00",
      "timestamp_display": "2026-04-27 06:00:49.910",
      "user": "xbai02b",
      "service": "bubble",
      "booking_date": "2026-04-29",
      "booking_hour": 14,
      "weekday": "Wednesday",
      "success": false,
      "message": "Unable to find any available Court",
      "error_type": "no_availability",
      "court_id": null,
      "court_number": null,
      "court_index": null,
      "response_time_ms": 503,
      "seconds_after_hour": 56.724,
      "booking_window": "6am",
      "thread_id": 1,
      "phase": "rapid",
      "attempt_number": 1,
      "session_age_seconds": 7.7,
      "copy_id": 3,
      "pid": 734725
    },
    {
      "timestamp": "2026-04-27T06:00:56.179819-04:00",
      "timestamp_display": "2026-04-27 06:00:56.179",
      "user": "xbai02b",
      "service": "bubble",
      "booking_date": "2026-04-29",
      "booking_hour": 14,
      "weekday": "Wednesday",
      "success": false,
      "message": "Unable to find any available Court",
      "error_type": "no_availability",
      "court_id": null,
      "court_number": null,
      "court_index": null,
      "response_time_ms": 495,
      "seconds_after_hour": 56.723,
      "booking_window": "6am",
      "thread_id": 5,
      "phase": "rapid",
      "attempt_number": 4,
      "session_age_seconds": 13.9,
      "copy_id": 3,
      "pid": 734725
    },
    {
      "timestamp": "2026-04-27T06:00:53.890633-04:00",
      "timestamp_display": "2026-04-27 06:00:53.890",
      "user": "xbai02b",
      "service": "bubble",
      "booking_date": "2026-04-29",
      "booking_hour": 17,
      "weekday": "Wednesday",
      "success": false,
      "message": "Unable to find any available Court",
      "error_type": "no_availability",
      "court_id": null,
      "court_number": null,
      "court_index": null,
      "response_time_ms": 351,
      "seconds_after_hour": 56.723,
      "booking_window": "6am",
      "thread_id": 5,
      "phase": "rapid",
      "attempt_number": 3,
      "session_age_seconds": 11.8,
      "copy_id": 3,
      "pid": 734725
    },
    {
      "timestamp": "2026-04-27T06:00:51.548247-04:00",
      "timestamp_display": "2026-04-27 06:00:51.548",
      "user": "xbai02b",
      "service": "bubble",
      "booking_date": "2026-04-29",
      "booking_hour": 14,
      "weekday": "Wednesday",
      "success": false,
      "message": "Unable to find any available Court",
      "error_type": "no_availability",
      "court_id": null,
      "court_number": null,
      "court_index": null,
      "response_time_ms": 379,
      "seconds_after_hour": 56.722,
      "booking_window": "6am",
      "thread_id": 5,
      "phase": "rapid",
      "attempt_number": 2,
      "session_age_seconds": 9.4,
      "copy_id": 3,
      "pid": 734725
    },
    {
      "timestamp": "2026-04-27T06:00:55.682314-04:00",
      "timestamp_display": "2026-04-27 06:00:55.682",
      "user": "xbai02b",
      "service": "bubble",
      "booking_date": "2026-04-29",
      "booking_hour": 14,
      "weekday": "Wednesday",
      "success": false,
      "message": "Unable to find any available Court",
      "error_type": "no_availability",
      "court_id": null,
      "court_number": null,
      "court_index": null,
      "response_time_ms": 357,
      "seconds_after_hour": 56.722,
      "booking_window": "6am",
      "thread_id": 3,
      "phase": "rapid",
      "attempt_number": 4,
      "session_age_seconds": 13.6,
      "copy_id": 3,
      "pid": 734725
    },
    {
      "timestamp": "2026-04-27T06:00:53.537358-04:00",
      "timestamp_display": "2026-04-27 06:00:53.537",
      "user": "xbai02b",
      "service": "bubble",
      "booking_date": "2026-04-29",
      "booking_hour": 17,
      "weekday": "Wednesday",
      "success": false,
      "message": "Unable to find any available Court",
      "error_type": "no_availability",
      "court_id": null,
      "court_number": null,
      "court_index": null,
      "response_time_ms": 564,
      "seconds_after_hour": 56.721,
      "booking_window": "6am",
      "thread_id": 3,
      "phase": "rapid",
      "attempt_number": 3,
      "session_age_seconds": 11.2,
      "copy_id": 3,
      "pid": 734725
    },
    {
      "timestamp": "2026-04-27T06:00:51.166869-04:00",
      "timestamp_display": "2026-04-27 06:00:51.166",
      "user": "xbai02b",
      "service": "bubble",
      "booking_date": "2026-04-29",
      "booking_hour": 14,
      "weekday": "Wednesday",
      "success": false,
      "message": "Unable to find any available Court",
      "error_type": "no_availability",
      "court_id": null,
      "court_number": null,
      "court_index": null,
      "response_time_ms": 338,
      "seconds_after_hour": 56.72,
      "booking_window": "6am",
      "thread_id": 3,
      "phase": "rapid",
      "attempt_number": 2,
      "session_age_seconds": 9.1,
      "copy_id": 3,
      "pid": 734725
    },
    {
      "timestamp": "2026-04-27T06:00:55.322834-04:00",
      "timestamp_display": "2026-04-27 06:00:55.322",
      "user": "xbai02b",
      "service": "bubble",
      "booking_date": "2026-04-29",
      "booking_hour": 14,
      "weekday": "Wednesday",
      "success": false,
      "message": "Unable to find any available Court",
      "error_type": "no_availability",
      "court_id": null,
      "court_number": null,
      "court_index": null,
      "response_time_ms": 562,
      "seconds_after_hour": 56.719,
      "booking_window": "6am",
      "thread_id": 2,
      "phase": "rapid",
      "attempt_number": 4,
      "session_age_seconds": 13.0,
      "copy_id": 3,
      "pid": 734725
    },
    {
      "timestamp": "2026-04-27T06:00:52.971670-04:00",
      "timestamp_display": "2026-04-27 06:00:52.971",
      "user": "xbai02b",
      "service": "bubble",
      "booking_date": "2026-04-29",
      "booking_hour": 17,
      "weekday": "Wednesday",
      "success": false,
      "message": "Unable to find any available Court",
      "error_type": "no_availability",
      "court_id": null,
      "court_number": null,
      "court_index": null,
      "response_time_ms": 521,
      "seconds_after_hour": 56.719,
      "booking_window": "6am",
      "thread_id": 2,
      "phase": "rapid",
      "attempt_number": 3,
      "session_age_seconds": 10.7,
      "copy_id": 3,
      "pid": 734725
    },
    {
      "timestamp": "2026-04-27T06:00:50.827191-04:00",
      "timestamp_display": "2026-04-27 06:00:50.827",
      "user": "xbai02b",
      "service": "bubble",
      "booking_date": "2026-04-29",
      "booking_hour": 14,
      "weekday": "Wednesday",
      "success": false,
      "message": "Unable to find any available Court",
      "error_type": "no_availability",
      "court_id": null,
      "court_number": null,
      "court_index": null,
      "response_time_ms": 354,
      "seconds_after_hour": 56.718,
      "booking_window": "6am",
      "thread_id": 2,
      "phase": "rapid",
      "attempt_number": 2,
      "session_age_seconds": 8.7,
      "copy_id": 3,
      "pid": 734725
    },
    {
      "timestamp": "2026-04-27T06:00:54.758061-04:00",
      "timestamp_display": "2026-04-27 06:00:54.758",
      "user": "xbai02b",
      "service": "bubble",
      "booking_date": "2026-04-29",
      "booking_hour": 17,
      "weekday": "Wednesday",
      "success": false,
      "message": "Unable to find any available Court",
      "error_type": "no_availability",
      "court_id": null,
      "court_number": null,
      "court_index": null,
      "response_time_ms": 357,
      "seconds_after_hour": 56.717,
      "booking_window": "6am",
      "thread_id": 4,
      "phase": "rapid",
      "attempt_number": 4,
      "session_age_seconds": 12.7,
      "copy_id": 3,
      "pid": 734725
    },
    {
      "timestamp": "2026-04-27T06:00:52.449503-04:00",
      "timestamp_display": "2026-04-27 06:00:52.449",
      "user": "xbai02b",
      "service": "bubble",
      "booking_date": "2026-04-29",
      "booking_hour": 14,
      "weekday": "Wednesday",
      "success": false,
      "message": "Unable to find any available Court",
      "error_type": "no_availability",
      "court_id": null,
      "court_number": null,
      "court_index": null,
      "response_time_ms": 549,
      "seconds_after_hour": 56.717,
      "booking_window": "6am",
      "thread_id": 4,
      "phase": "rapid",
      "attempt_number": 3,
      "session_age_seconds": 10.2,
      "copy_id": 3,
      "pid": 734725
    },
    {
      "timestamp": "2026-04-27T06:00:50.471417-04:00",
      "timestamp_display": "2026-04-27 06:00:50.471",
      "user": "xbai02b",
      "service": "bubble",
      "booking_date": "2026-04-29",
      "booking_hour": 17,
      "weekday": "Wednesday",
      "success": false,
      "message": "Unable to find any available Court",
      "error_type": "no_availability",
      "court_id": null,
      "court_number": null,
      "court_index": null,
      "response_time_ms": 559,
      "seconds_after_hour": 56.716,
      "booking_window": "6am",
      "thread_id": 4,
      "phase": "rapid",
      "attempt_number": 2,
      "session_age_seconds": 8.2,
      "copy_id": 3,
      "pid": 734725
    },
    {
      "timestamp": "2026-04-27T06:00:49.404934-04:00",
      "timestamp_display": "2026-04-27 06:00:49.404",
      "user": "xbai02b",
      "service": "bubble",
      "booking_date": "2026-04-29",
      "booking_hour": 14,
      "weekday": "Wednesday",
      "success": false,
      "message": "Unable to find any available Court",
      "error_type": "no_availability",
      "court_id": null,
      "court_number": null,
      "court_index": null,
      "response_time_ms": 526,
      "seconds_after_hour": 56.715,
      "booking_window": "6am",
      "thread_id": 4,
      "phase": "rapid",
      "attempt_number": 1,
      "session_age_seconds": 7.2,
      "copy_id": 3,
      "pid": 734725
    },
    {
      "timestamp": "2026-04-27T06:00:48.868825-04:00",
      "timestamp_display": "2026-04-27 06:00:48.868",
      "user": "xbai02b",
      "service": "bubble",
      "booking_date": "2026-04-29",
      "booking_hour": 14,
      "weekday": "Wednesday",
      "success": false,
      "message": "Unable to find any available Court",
      "error_type": "no_availability",
      "court_id": null,
      "court_number": null,
      "court_index": null,
      "response_time_ms": 346,
      "seconds_after_hour": 48.879,
      "booking_window": "6am",
      "thread_id": 2,
      "phase": "rapid",
      "attempt_number": 4,
      "session_age_seconds": 20.1,
      "copy_id": 2,
      "pid": 734684
    },
    {
      "timestamp": "2026-04-27T06:00:46.755717-04:00",
      "timestamp_display": "2026-04-27 06:00:46.755",
      "user": "xbai02b",
      "service": "bubble",
      "booking_date": "2026-04-29",
      "booking_hour": 17,
      "weekday": "Wednesday",
      "success": false,
      "message": "Unable to find any available Court",
      "error_type": "no_availability",
      "court_id": null,
      "court_number": null,
      "court_index": null,
      "response_time_ms": 369,
      "seconds_after_hour": 48.879,
      "booking_window": "6am",
      "thread_id": 2,
      "phase": "rapid",
      "attempt_number": 3,
      "session_age_seconds": 18.0,
      "copy_id": 2,
      "pid": 734684
    },
    {
      "timestamp": "2026-04-27T06:00:45.024890-04:00",
      "timestamp_display": "2026-04-27 06:00:45.024",
      "user": "xbai02b",
      "service": "bubble",
      "booking_date": "2026-04-29",
      "booking_hour": 14,
      "weekday": "Wednesday",
      "success": false,
      "message": "Unable to find any available Court",
      "error_type": "no_availability",
      "court_id": null,
      "court_number": null,
      "court_index": null,
      "response_time_ms": 510,
      "seconds_after_hour": 48.878,
      "booking_window": "6am",
      "thread_id": 2,
      "phase": "rapid",
      "attempt_number": 2,
      "session_age_seconds": 16.1,
      "copy_id": 2,
      "pid": 734684
    },
    {
      "timestamp": "2026-04-27T06:00:43.503863-04:00",
      "timestamp_display": "2026-04-27 06:00:43.503",
      "user": "xbai02b",
      "service": "bubble",
      "booking_date": "2026-04-29",
      "booking_hour": 17,
      "weekday": "Wednesday",
      "success": false,
      "message": "Unable to find any available Court",
      "error_type": "no_availability",
      "court_id": null,
      "court_number": null,
      "court_index": null,
      "response_time_ms": 496,
      "seconds_after_hour": 48.878,
      "booking_window": "6am",
      "thread_id": 2,
      "phase": "rapid",
      "attempt_number": 1,
      "session_age_seconds": 14.6,
      "copy_id": 2,
      "pid": 734684
    },
    {
      "timestamp": "2026-04-27T06:00:48.519858-04:00",
      "timestamp_display": "2026-04-27 06:00:48.519",
      "user": "xbai02b",
      "service": "bubble",
      "booking_date": "2026-04-29",
      "booking_hour": 14,
      "weekday": "Wednesday",
      "success": false,
      "message": "Unable to find any available Court",
      "error_type": "no_availability",
      "court_id": null,
      "court_number": null,
      "court_index": null,
      "response_time_ms": 534,
      "seconds_after_hour": 48.877,
      "booking_window": "6am",
      "thread_id": 5,
      "phase": "rapid",
      "attempt_number": 4,
      "session_age_seconds": 19.6,
      "copy_id": 2,
      "pid": 734684
    },
    {
      "timestamp": "2026-04-27T06:00:46.385048-04:00",
      "timestamp_display": "2026-04-27 06:00:46.385",
      "user": "xbai02b",
      "service": "bubble",
      "booking_date": "2026-04-29",
      "booking_hour": 17,
      "weekday": "Wednesday",
      "success": false,
      "message": "Unable to find any available Court",
      "error_type": "no_availability",
      "court_id": null,
      "court_number": null,
      "court_index": null,
      "response_time_ms": 346,
      "seconds_after_hour": 48.877,
      "booking_window": "6am",
      "thread_id": 5,
      "phase": "rapid",
      "attempt_number": 3,
      "session_age_seconds": 17.6,
      "copy_id": 2,
      "pid": 734684
    },
    {
      "timestamp": "2026-04-27T06:00:44.512833-04:00",
      "timestamp_display": "2026-04-27 06:00:44.512",
      "user": "xbai02b",
      "service": "bubble",
      "booking_date": "2026-04-29",
      "booking_hour": 14,
      "weekday": "Wednesday",
      "success": false,
      "message": "Unable to find any available Court",
      "error_type": "no_availability",
      "court_id": null,
      "court_number": null,
      "court_index": null,
      "response_time_ms": 332,
      "seconds_after_hour": 48.876,
      "booking_window": "6am",
      "thread_id": 5,
      "phase": "rapid",
      "attempt_number": 2,
      "session_age_seconds": 15.8,
      "copy_id": 2,
      "pid": 734684
    },
    {
      "timestamp": "2026-04-27T06:00:47.983104-04:00",
      "timestamp_display": "2026-04-27 06:00:47.983",
      "user": "xbai02b",
      "service": "bubble",
      "booking_date": "2026-04-29",
      "booking_hour": 17,
      "weekday": "Wednesday",
      "success": false,
      "message": "Unable to find any available Court",
      "error_type": "no_availability",
      "court_id": null,
      "court_number": null,
      "court_index": null,
      "response_time_ms": 513,
      "seconds_after_hour": 48.876,
      "booking_window": "6am",
      "thread_id": 1,
      "phase": "rapid",
      "attempt_number": 4,
      "session_age_seconds": 19.0,
      "copy_id": 2,
      "pid": 734684
    },
    {
      "timestamp": "2026-04-27T06:00:46.036831-04:00",
      "timestamp_display": "2026-04-27 06:00:46.036",
      "user": "xbai02b",
      "service": "bubble",
      "booking_date": "2026-04-29",
      "booking_hour": 14,
      "weekday": "Wednesday",
      "success": false,
      "message": "Unable to find any available Court",
      "error_type": "no_availability",
      "court_id": null,
      "court_number": null,
      "court_index": null,
      "response_time_ms": 347,
      "seconds_after_hour": 48.875,
      "booking_window": "6am",
      "thread_id": 1,
      "phase": "rapid",
      "attempt_number": 3,
      "session_age_seconds": 17.2,
      "copy_id": 2,
      "pid": 734684
    },
    {
      "timestamp": "2026-04-27T06:00:47.467417-04:00",
      "timestamp_display": "2026-04-27 06:00:47.467",
      "user": "xbai02b",
      "service": "bubble",
      "booking_date": "2026-04-29",
      "booking_hour": 17,
      "weekday": "Wednesday",
      "success": false,
      "message": "Unable to find any available Court",
      "error_type": "no_availability",
      "court_id": null,
      "court_number": null,
      "court_index": null,
      "response_time_ms": 378,
      "seconds_after_hour": 48.875,
      "booking_window": "6am",
      "thread_id": 4,
      "phase": "rapid",
      "attempt_number": 4,
      "session_age_seconds": 18.8,
      "copy_id": 2,
      "pid": 734684
    },
    {
      "timestamp": "2026-04-27T06:00:45.687191-04:00",
      "timestamp_display": "2026-04-27 06:00:45.687",
      "user": "xbai02b",
      "service": "bubble",
      "booking_date": "2026-04-29",
      "booking_hour": 14,
      "weekday": "Wednesday",
      "success": false,
      "message": "Unable to find any available Court",
      "error_type": "no_availability",
      "court_id": null,
      "court_number": null,
      "court_index": null,
      "response_time_ms": 315,
      "seconds_after_hour": 48.874,
      "booking_window": "6am",
      "thread_id": 4,
      "phase": "rapid",
      "attempt_number": 3,
      "session_age_seconds": 17.1,
      "copy_id": 2,
      "pid": 734684
    },
    {
      "timestamp": "2026-04-27T06:00:44.179055-04:00",
      "timestamp_display": "2026-04-27 06:00:44.179",
      "user": "xbai02b",
      "service": "bubble",
      "booking_date": "2026-04-29",
      "booking_hour": 17,
      "weekday": "Wednesday",
      "success": false,
      "message": "Unable to find any available Court",
      "error_type": "no_availability",
      "court_id": null,
      "court_number": null,
      "court_index": null,
      "response_time_ms": 331,
      "seconds_after_hour": 48.873,
      "booking_window": "6am",
      "thread_id": 4,
      "phase": "rapid",
      "attempt_number": 2,
      "session_age_seconds": 15.5,
      "copy_id": 2,
      "pid": 734684
    },
    {
      "timestamp": "2026-04-27T06:00:47.087290-04:00",
      "timestamp_display": "2026-04-27 06:00:47.087",
      "user": "xbai02b",
      "service": "bubble",
      "booking_date": "2026-04-29",
      "booking_hour": 14,
      "weekday": "Wednesday",
      "success": false,
      "message": "Unable to find any available Court",
      "error_type": "no_availability",
      "court_id": null,
      "court_number": null,
      "court_index": null,
      "response_time_ms": 329,
      "seconds_after_hour": 48.873,
      "booking_window": "6am",
      "thread_id": 3,
      "phase": "rapid",
      "attempt_number": 4,
      "session_age_seconds": 18.4,
      "copy_id": 2,
      "pid": 734684
    },
    {
      "timestamp": "2026-04-27T06:00:45.369619-04:00",
      "timestamp_display": "2026-04-27 06:00:45.369",
      "user": "xbai02b",
      "service": "bubble",
      "booking_date": "2026-04-29",
      "booking_hour": 17,
      "weekday": "Wednesday",
      "success": false,
      "message": "Unable to find any available Court",
      "error_type": "no_availability",
      "court_id": null,
      "court_number": null,
      "court_index": null,
      "response_time_ms": 343,
      "seconds_after_hour": 48.872,
      "booking_window": "6am",
      "thread_id": 3,
      "phase": "rapid",
      "attempt_number": 3,
      "session_age_seconds": 16.7,
      "copy_id": 2,
      "pid": 734684
    },
    {
      "timestamp": "2026-04-27T06:00:43.846346-04:00",
      "timestamp_display": "2026-04-27 06:00:43.846",
      "user": "xbai02b",
      "service": "bubble",
      "booking_date": "2026-04-29",
      "booking_hour": 14,
      "weekday": "Wednesday",
      "success": false,
      "message": "Unable to find any available Court",
      "error_type": "no_availability",
      "court_id": null,
      "court_number": null,
      "court_index": null,
      "response_time_ms": 340,
      "seconds_after_hour": 48.87,
      "booking_window": "6am",
      "thread_id": 3,
      "phase": "rapid",
      "attempt_number": 2,
      "session_age_seconds": 15.2,
      "copy_id": 2,
      "pid": 734684
    },
    {
      "timestamp": "2026-04-27T06:00:43.005650-04:00",
      "timestamp_display": "2026-04-27 06:00:43.005",
      "user": "xbai02b",
      "service": "bubble",
      "booking_date": "2026-04-29",
      "booking_hour": 17,
      "weekday": "Wednesday",
      "success": false,
      "message": "Unable to find any available Court",
      "error_type": "no_availability",
      "court_id": null,
      "court_number": null,
      "court_index": null,
      "response_time_ms": 366,
      "seconds_after_hour": 43.017,
      "booking_window": "6am",
      "thread_id": 1,
      "phase": "rapid",
      "attempt_number": 4,
      "session_age_seconds": 9.1,
      "copy_id": 1,
      "pid": 734680
    },
    {
      "timestamp": "2026-04-27T06:00:41.044094-04:00",
      "timestamp_display": "2026-04-27 06:00:41.044",
      "user": "xbai02b",
      "service": "bubble",
      "booking_date": "2026-04-29",
      "booking_hour": 14,
      "weekday": "Wednesday",
      "success": false,
      "message": "Unable to find any available Court",
      "error_type": "no_availability",
      "court_id": null,
      "court_number": null,
      "court_index": null,
      "response_time_ms": 379,
      "seconds_after_hour": 43.016,
      "booking_window": "6am",
      "thread_id": 1,
      "phase": "rapid",
      "attempt_number": 3,
      "session_age_seconds": 7.2,
      "copy_id": 1,
      "pid": 734680
    },
    {
      "timestamp": "2026-04-27T06:00:39.150645-04:00",
      "timestamp_display": "2026-04-27 06:00:39.150",
      "user": "xbai02b",
      "service": "bubble",
      "booking_date": "2026-04-29",
      "booking_hour": 17,
      "weekday": "Wednesday",
      "success": false,
      "message": "Unable to find any available Court",
      "error_type": "no_availability",
      "court_id": null,
      "court_number": null,
      "court_index": null,
      "response_time_ms": 527,
      "seconds_after_hour": 43.016,
      "booking_window": "6am",
      "thread_id": 1,
      "phase": "rapid",
      "attempt_number": 2,
      "session_age_seconds": 5.1,
      "copy_id": 1,
      "pid": 734680
    },
    {
      "timestamp": "2026-04-27T06:00:37.039289-04:00",
      "timestamp_display": "2026-04-27 06:00:37.039",
      "user": "xbai02b",
      "service": "bubble",
      "booking_date": "2026-04-29",
      "booking_hour": 14,
      "weekday": "Wednesday",
      "success": false,
      "message": "Unable to find any available Court",
      "error_type": "no_availability",
      "court_id": null,
      "court_number": null,
      "court_index": null,
      "response_time_ms": 514,
      "seconds_after_hour": 43.015,
      "booking_window": "6am",
      "thread_id": 1,
      "phase": "rapid",
      "attempt_number": 1,
      "session_age_seconds": 3.0,
      "copy_id": 1,
      "pid": 734680
    },
    {
      "timestamp": "2026-04-27T06:00:42.637993-04:00",
      "timestamp_display": "2026-04-27 06:00:42.637",
      "user": "xbai02b",
      "service": "bubble",
      "booking_date": "2026-04-29",
      "booking_hour": 14,
      "weekday": "Wednesday",
      "success": false,
      "message": "Unable to find any available Court",
      "error_type": "no_availability",
      "court_id": null,
      "court_number": null,
      "court_index": null,
      "response_time_ms": 339,
      "seconds_after_hour": 43.015,
      "booking_window": "6am",
      "thread_id": 2,
      "phase": "rapid",
      "attempt_number": 4,
      "session_age_seconds": 8.8,
      "copy_id": 1,
      "pid": 734680
    },
    {
      "timestamp": "2026-04-27T06:00:40.663162-04:00",
      "timestamp_display": "2026-04-27 06:00:40.663",
      "user": "xbai02b",
      "service": "bubble",
      "booking_date": "2026-04-29",
      "booking_hour": 17,
      "weekday": "Wednesday",
      "success": false,
      "message": "Unable to find any available Court",
      "error_type": "no_availability",
      "court_id": null,
      "court_number": null,
      "court_index": null,
      "response_time_ms": 335,
      "seconds_after_hour": 43.014,
      "booking_window": "6am",
      "thread_id": 2,
      "phase": "rapid",
      "attempt_number": 3,
      "session_age_seconds": 6.8,
      "copy_id": 1,
      "pid": 734680
    },
    {
      "timestamp": "2026-04-27T06:00:38.621817-04:00",
      "timestamp_display": "2026-04-27 06:00:38.621",
      "user": "xbai02b",
      "service": "bubble",
      "booking_date": "2026-04-29",
      "booking_hour": 14,
      "weekday": "Wednesday",
      "success": false,
      "message": "Unable to find any available Court",
      "error_type": "no_availability",
      "court_id": null,
      "court_number": null,
      "court_index": null,
      "response_time_ms": 529,
      "seconds_after_hour": 43.014,
      "booking_window": "6am",
      "thread_id": 2,
      "phase": "rapid",
      "attempt_number": 2,
      "session_age_seconds": 4.6,
      "copy_id": 1,
      "pid": 734680
    },
    {
      "timestamp": "2026-04-27T06:00:36.523352-04:00",
      "timestamp_display": "2026-04-27 06:00:36.523",
      "user": "xbai02b",
      "service": "bubble",
      "booking_date": "2026-04-29",
      "booking_hour": 17,
      "weekday": "Wednesday",
      "success": false,
      "message": "Unable to find any available Court",
      "error_type": "no_availability",
      "court_id": null,
      "court_number": null,
      "court_index": null,
      "response_time_ms": 329,
      "seconds_after_hour": 43.013,
      "booking_window": "6am",
      "thread_id": 2,
      "phase": "rapid",
      "attempt_number": 1,
      "session_age_seconds": 2.7,
      "copy_id": 1,
      "pid": 734680
    },
    {
      "timestamp": "2026-04-27T06:00:42.296842-04:00",
      "timestamp_display": "2026-04-27 06:00:42.296",
      "user": "xbai02b",
      "service": "bubble",
      "booking_date": "2026-04-29",
      "booking_hour": 14,
      "weekday": "Wednesday",
      "success": false,
      "message": "Unable to find any available Court",
      "error_type": "no_availability",
      "court_id": null,
      "court_number": null,
      "court_index": null,
      "response_time_ms": 331,
      "seconds_after_hour": 43.013,
      "booking_window": "6am",
      "thread_id": 5,
      "phase": "rapid",
      "attempt_number": 4,
      "session_age_seconds": 8.6,
      "copy_id": 1,
      "pid": 734680
    },
    {
      "timestamp": "2026-04-27T06:00:40.326659-04:00",
      "timestamp_display": "2026-04-27 06:00:40.326",
      "user": "xbai02b",
      "service": "bubble",
      "booking_date": "2026-04-29",
      "booking_hour": 17,
      "weekday": "Wednesday",
      "success": false,
      "message": "Unable to find any available Court",
      "error_type": "no_availability",
      "court_id": null,
      "court_number": null,
      "court_index": null,
      "response_time_ms": 331,
      "seconds_after_hour": 43.012,
      "booking_window": "6am",
      "thread_id": 5,
      "phase": "rapid",
      "attempt_number": 3,
      "session_age_seconds": 6.6,
      "copy_id": 1,
      "pid": 734680
    },
    {
      "timestamp": "2026-04-27T06:00:38.090258-04:00",
      "timestamp_display": "2026-04-27 06:00:38.090",
      "user": "xbai02b",
      "service": "bubble",
      "booking_date": "2026-04-29",
      "booking_hour": 14,
      "weekday": "Wednesday",
      "success": false,
      "message": "Unable to find any available Court",
      "error_type": "no_availability",
      "court_id": null,
      "court_number": null,
      "court_index": null,
      "response_time_ms": 334,
      "seconds_after_hour": 43.012,
      "booking_window": "6am",
      "thread_id": 5,
      "phase": "rapid",
      "attempt_number": 2,
      "session_age_seconds": 4.4,
      "copy_id": 1,
      "pid": 734680
    },
    {
      "timestamp": "2026-04-27T06:00:36.192436-04:00",
      "timestamp_display": "2026-04-27 06:00:36.192",
      "user": "xbai02b",
      "service": "bubble",
      "booking_date": "2026-04-29",
      "booking_hour": 17,
      "weekday": "Wednesday",
      "success": false,
      "message": "Unable to find any available Court",
      "error_type": "no_availability",
      "court_id": null,
      "court_number": null,
      "court_index": null,
      "response_time_ms": 536,
      "seconds_after_hour": 43.011,
      "booking_window": "6am",
      "thread_id": 5,
      "phase": "rapid",
      "attempt_number": 1,
      "session_age_seconds": 2.3,
      "copy_id": 1,
      "pid": 734680
    },
    {
      "timestamp": "2026-04-27T06:00:41.963899-04:00",
      "timestamp_display": "2026-04-27 06:00:41.963",
      "user": "xbai02b",
      "service": "bubble",
      "booking_date": "2026-04-29",
      "booking_hour": 14,
      "weekday": "Wednesday",
      "success": false,
      "message": "Unable to find any available Court",
      "error_type": "no_availability",
      "court_id": null,
      "court_number": null,
      "court_index": null,
      "response_time_ms": 388,
      "seconds_after_hour": 43.011,
      "booking_window": "6am",
      "thread_id": 3,
      "phase": "rapid",
      "attempt_number": 4,
      "session_age_seconds": 8.2,
      "copy_id": 1,
      "pid": 734680
    },
    {
      "timestamp": "2026-04-27T06:00:39.994626-04:00",
      "timestamp_display": "2026-04-27 06:00:39.994",
      "user": "xbai02b",
      "service": "bubble",
      "booking_date": "2026-04-29",
      "booking_hour": 17,
      "weekday": "Wednesday",
      "success": false,
      "message": "Unable to find any available Court",
      "error_type": "no_availability",
      "court_id": null,
      "court_number": null,
      "court_index": null,
      "response_time_ms": 346,
      "seconds_after_hour": 43.01,
      "booking_window": "6am",
      "thread_id": 3,
      "phase": "rapid",
      "attempt_number": 3,
      "session_age_seconds": 6.3,
      "copy_id": 1,
      "pid": 734680
    },
    {
      "timestamp": "2026-04-27T06:00:37.754350-04:00",
      "timestamp_display": "2026-04-27 06:00:37.754",
      "user": "xbai02b",
      "service": "bubble",
      "booking_date": "2026-04-29",
      "booking_hour": 14,
      "weekday": "Wednesday",
      "success": false,
      "message": "Unable to find any available Court",
      "error_type": "no_availability",
      "court_id": null,
      "court_number": null,
      "court_index": null,
      "response_time_ms": 361,
      "seconds_after_hour": 43.01,
      "booking_window": "6am",
      "thread_id": 3,
      "phase": "rapid",
      "attempt_number": 2,
      "session_age_seconds": 4.1,
      "copy_id": 1,
      "pid": 734680
    },
    {
      "timestamp": "2026-04-27T06:00:35.654508-04:00",
      "timestamp_display": "2026-04-27 06:00:35.654",
      "user": "xbai02b",
      "service": "bubble",
      "booking_date": "2026-04-29",
      "booking_hour": 17,
      "weekday": "Wednesday",
      "success": false,
      "message": "Unable to find any available Court",
      "error_type": "no_availability",
      "court_id": null,
      "court_number": null,
      "court_index": null,
      "response_time_ms": 524,
      "seconds_after_hour": 43.009,
      "booking_window": "6am",
      "thread_id": 3,
      "phase": "rapid",
      "attempt_number": 1,
      "session_age_seconds": 1.8,
      "copy_id": 1,
      "pid": 734680
    },
    {
      "timestamp": "2026-04-27T06:00:41.574030-04:00",
      "timestamp_display": "2026-04-27 06:00:41.574",
      "user": "xbai02b",
      "service": "bubble",
      "booking_date": "2026-04-29",
      "booking_hour": 17,
      "weekday": "Wednesday",
      "success": false,
      "message": "Unable to find any available Court",
      "error_type": "no_availability",
      "court_id": null,
      "court_number": null,
      "court_index": null,
      "response_time_ms": 529,
      "seconds_after_hour": 43.009,
      "booking_window": "6am",
      "thread_id": 4,
      "phase": "rapid",
      "attempt_number": 4,
      "session_age_seconds": 7.7,
      "copy_id": 1,
      "pid": 734680
    },
    {
      "timestamp": "2026-04-27T06:00:39.647063-04:00",
      "timestamp_display": "2026-04-27 06:00:39.647",
      "user": "xbai02b",
      "service": "bubble",
      "booking_date": "2026-04-29",
      "booking_hour": 14,
      "weekday": "Wednesday",
      "success": false,
      "message": "Unable to find any available Court",
      "error_type": "no_availability",
      "court_id": null,
      "court_number": null,
      "court_index": null,
      "response_time_ms": 495,
      "seconds_after_hour": 43.008,
      "booking_window": "6am",
      "thread_id": 4,
      "phase": "rapid",
      "attempt_number": 3,
      "session_age_seconds": 5.8,
      "copy_id": 1,
      "pid": 734680
    }
  ],
  "next_booking": {
    "next_window": "2026-04-28T06:00:00-04:00",
    "next_window_display": "2026-04-28 06:00 EDT",
    "target_date": "2026-04-30",
    "target_weekday": "Thursday",
    "planned_attempts": [
      {
        "user": "xbai02b",
        "date": "2026-04-30",
        "weekday": "Thursday",
        "hour": 14,
        "time": "14:00"
      },
      {
        "user": "xbai02b",
        "date": "2026-04-30",
        "weekday": "Thursday",
        "hour": 15,
        "time": "15:00"
      },
      {
        "user": "xbai02b",
        "date": "2026-04-30",
        "weekday": "Thursday",
        "hour": 17,
        "time": "17:00"
      },
      {
        "user": "zwang43b",
        "date": "2026-04-30",
        "weekday": "Thursday",
        "hour": 15,
        "time": "15:00"
      },
      {
        "user": "zwang43b",
        "date": "2026-04-30",
        "weekday": "Thursday",
        "hour": 14,
        "time": "14:00"
      },
      {
        "user": "zwang43b",
        "date": "2026-04-30",
        "weekday": "Thursday",
        "hour": 17,
        "time": "17:00"
      }
    ]
  },
  "stats": {
    "total_attempts": 109712,
    "successful_attempts": 243,
    "success_rate": 0.0022
  }
}