{
  "last_sync": "2026-04-26T09:20:17.968260",
  "script_status": {
    "xbai02b": {
      "running": true,
      "copies": 3,
      "pids": [
        12740,
        12742,
        12744
      ],
      "last_seen": "2026-04-26T09:20:03.253648",
      "paused": false
    },
    "zwang43b": {
      "running": true,
      "copies": 3,
      "pids": [
        12754,
        12774,
        12780
      ],
      "last_seen": "2026-04-26T09:20:03.253662",
      "paused": false
    }
  },
  "total_copies": 6,
  "users": [
    {
      "name": "xbai02b",
      "status": "RUNNING",
      "instances": 3,
      "paused": false
    },
    {
      "name": "zwang43b",
      "status": "RUNNING",
      "instances": 3,
      "paused": false
    }
  ],
  "reservations": [
    {
      "date": "2026-04-26",
      "time": "14:00",
      "court": "Bubble Court 4",
      "activity": "Tennis Reservation (Bubble Court 4)",
      "weekday": "Sun",
      "cancel_id": "856158",
      "user": "xbai02b",
      "reservation_id": "xbai02b_2026-04-26_1400",
      "booked_at": "2026-04-24T06:00:03.433372-04:00"
    },
    {
      "date": "2026-04-26",
      "time": "15:00",
      "court": "Bubble Court 2",
      "activity": "Tennis Reservation (Bubble Court 2)",
      "weekday": "Sun",
      "cancel_id": "856166",
      "user": "zwang43b",
      "reservation_id": "zwang43b_2026-04-26_1500",
      "booked_at": "2026-04-24T06:00:05.049091-04:00"
    },
    {
      "date": "2026-04-27",
      "time": "15:00",
      "court": "Bubble Court 2",
      "activity": "Tennis Reservation (Bubble Court 2)",
      "weekday": "Mon",
      "cancel_id": "856812",
      "user": "xbai02b",
      "reservation_id": "xbai02b_2026-04-27_1500",
      "booked_at": "2026-04-25T06:00:03.531564-04:00"
    },
    {
      "date": "2026-04-27",
      "time": "15:00",
      "court": "Bubble Court 1",
      "activity": "Tennis Reservation (Bubble Court 1)",
      "weekday": "Mon",
      "cancel_id": "856807",
      "user": "zwang43b",
      "reservation_id": "zwang43b_2026-04-27_1500",
      "booked_at": "2026-04-25T06:00:02.561818-04:00"
    },
    {
      "date": "2026-04-28",
      "time": "14:00",
      "court": "Bubble Court 2",
      "activity": "Tennis Reservation (Bubble Court 2)",
      "weekday": "Tue",
      "cancel_id": "857313",
      "user": "xbai02b",
      "reservation_id": "xbai02b_2026-04-28_1400",
      "booked_at": "2026-04-26T06:00:03.840915-04:00"
    },
    {
      "date": "2026-04-28",
      "time": "15:00",
      "court": "Bubble Court 1",
      "activity": "Tennis Reservation (Bubble Court 1)",
      "weekday": "Tue",
      "cancel_id": "857315",
      "user": "zwang43b",
      "reservation_id": "zwang43b_2026-04-28_1500",
      "booked_at": "2026-04-26T06:00:04.021485-04:00"
    }
  ],
  "bookings": [
    {
      "timestamp": "2026-04-26T06:00:52.167380-04:00",
      "timestamp_display": "2026-04-26 06:00:52.167",
      "user": "xbai02b",
      "service": "bubble",
      "booking_date": "2026-04-28",
      "booking_hour": 17,
      "weekday": "Tuesday",
      "success": false,
      "message": "Unable to find any available Court",
      "error_type": "no_availability",
      "court_id": null,
      "court_number": null,
      "court_index": null,
      "response_time_ms": 533,
      "seconds_after_hour": 52.378,
      "booking_window": "6am",
      "thread_id": 4,
      "phase": "rapid",
      "attempt_number": 6,
      "session_age_seconds": 23.3,
      "copy_id": 2,
      "pid": 12742
    },
    {
      "timestamp": "2026-04-26T06:00:50.742503-04:00",
      "timestamp_display": "2026-04-26 06:00:50.742",
      "user": "xbai02b",
      "service": "bubble",
      "booking_date": "2026-04-28",
      "booking_hour": 15,
      "weekday": "Tuesday",
      "success": false,
      "message": "Unable to find any available Court",
      "error_type": "no_availability",
      "court_id": null,
      "court_number": null,
      "court_index": null,
      "response_time_ms": 320,
      "seconds_after_hour": 52.369,
      "booking_window": "6am",
      "thread_id": 4,
      "phase": "rapid",
      "attempt_number": 5,
      "session_age_seconds": 22.1,
      "copy_id": 2,
      "pid": 12742
    },
    {
      "timestamp": "2026-04-26T06:00:44.537095-04:00",
      "timestamp_display": "2026-04-26 06:00:44.537",
      "user": "xbai02b",
      "service": "bubble",
      "booking_date": "2026-04-28",
      "booking_hour": 14,
      "weekday": "Tuesday",
      "success": false,
      "message": "Unable to find any available Court",
      "error_type": "no_availability",
      "court_id": null,
      "court_number": null,
      "court_index": null,
      "response_time_ms": 355,
      "seconds_after_hour": 52.361,
      "booking_window": "6am",
      "thread_id": 4,
      "phase": "rapid",
      "attempt_number": 4,
      "session_age_seconds": 15.9,
      "copy_id": 2,
      "pid": 12742
    },
    {
      "timestamp": "2026-04-26T06:00:42.657212-04:00",
      "timestamp_display": "2026-04-26 06:00:42.657",
      "user": "xbai02b",
      "service": "bubble",
      "booking_date": "2026-04-28",
      "booking_hour": 17,
      "weekday": "Tuesday",
      "success": false,
      "message": "Unable to find any available Court",
      "error_type": "no_availability",
      "court_id": null,
      "court_number": null,
      "court_index": null,
      "response_time_ms": 343,
      "seconds_after_hour": 52.352,
      "booking_window": "6am",
      "thread_id": 4,
      "phase": "rapid",
      "attempt_number": 3,
      "session_age_seconds": 14.0,
      "copy_id": 2,
      "pid": 12742
    },
    {
      "timestamp": "2026-04-26T06:00:42.309737-04:00",
      "timestamp_display": "2026-04-26 06:00:42.309",
      "user": "xbai02b",
      "service": "bubble",
      "booking_date": "2026-04-28",
      "booking_hour": 15,
      "weekday": "Tuesday",
      "success": false,
      "message": "Unable to find any available Court",
      "error_type": "no_availability",
      "court_id": null,
      "court_number": null,
      "court_index": null,
      "response_time_ms": 330,
      "seconds_after_hour": 52.344,
      "booking_window": "6am",
      "thread_id": 4,
      "phase": "rapid",
      "attempt_number": 2,
      "session_age_seconds": 13.7,
      "copy_id": 2,
      "pid": 12742
    },
    {
      "timestamp": "2026-04-26T06:00:51.628833-04:00",
      "timestamp_display": "2026-04-26 06:00:51.628",
      "user": "xbai02b",
      "service": "bubble",
      "booking_date": "2026-04-28",
      "booking_hour": 15,
      "weekday": "Tuesday",
      "success": false,
      "message": "Unable to find any available Court",
      "error_type": "no_availability",
      "court_id": null,
      "court_number": null,
      "court_index": null,
      "response_time_ms": 373,
      "seconds_after_hour": 52.335,
      "booking_window": "6am",
      "thread_id": 3,
      "phase": "rapid",
      "attempt_number": 6,
      "session_age_seconds": 23.0,
      "copy_id": 2,
      "pid": 12742
    },
    {
      "timestamp": "2026-04-26T06:00:46.088857-04:00",
      "timestamp_display": "2026-04-26 06:00:46.088",
      "user": "xbai02b",
      "service": "bubble",
      "booking_date": "2026-04-28",
      "booking_hour": 14,
      "weekday": "Tuesday",
      "success": false,
      "message": "Unable to find any available Court",
      "error_type": "no_availability",
      "court_id": null,
      "court_number": null,
      "court_index": null,
      "response_time_ms": 513,
      "seconds_after_hour": 52.328,
      "booking_window": "6am",
      "thread_id": 3,
      "phase": "rapid",
      "attempt_number": 5,
      "session_age_seconds": 17.4,
      "copy_id": 2,
      "pid": 12742
    },
    {
      "timestamp": "2026-04-26T06:00:43.839847-04:00",
      "timestamp_display": "2026-04-26 06:00:43.839",
      "user": "xbai02b",
      "service": "bubble",
      "booking_date": "2026-04-28",
      "booking_hour": 17,
      "weekday": "Tuesday",
      "success": false,
      "message": "Unable to find any available Court",
      "error_type": "no_availability",
      "court_id": null,
      "court_number": null,
      "court_index": null,
      "response_time_ms": 330,
      "seconds_after_hour": 52.32,
      "booking_window": "6am",
      "thread_id": 3,
      "phase": "rapid",
      "attempt_number": 4,
      "session_age_seconds": 15.3,
      "copy_id": 2,
      "pid": 12742
    },
    {
      "timestamp": "2026-04-26T06:00:41.976848-04:00",
      "timestamp_display": "2026-04-26 06:00:41.976",
      "user": "xbai02b",
      "service": "bubble",
      "booking_date": "2026-04-28",
      "booking_hour": 15,
      "weekday": "Tuesday",
      "success": false,
      "message": "Unable to find any available Court",
      "error_type": "no_availability",
      "court_id": null,
      "court_number": null,
      "court_index": null,
      "response_time_ms": 325,
      "seconds_after_hour": 52.312,
      "booking_window": "6am",
      "thread_id": 3,
      "phase": "rapid",
      "attempt_number": 3,
      "session_age_seconds": 13.4,
      "copy_id": 2,
      "pid": 12742
    },
    {
      "timestamp": "2026-04-26T06:00:40.285322-04:00",
      "timestamp_display": "2026-04-26 06:00:40.285",
      "user": "xbai02b",
      "service": "bubble",
      "booking_date": "2026-04-28",
      "booking_hour": 14,
      "weekday": "Tuesday",
      "success": false,
      "message": "Unable to find any available Court",
      "error_type": "no_availability",
      "court_id": null,
      "court_number": null,
      "court_index": null,
      "response_time_ms": 525,
      "seconds_after_hour": 52.304,
      "booking_window": "6am",
      "thread_id": 3,
      "phase": "rapid",
      "attempt_number": 2,
      "session_age_seconds": 11.5,
      "copy_id": 2,
      "pid": 12742
    },
    {
      "timestamp": "2026-04-26T06:00:51.251035-04:00",
      "timestamp_display": "2026-04-26 06:00:51.251",
      "user": "xbai02b",
      "service": "bubble",
      "booking_date": "2026-04-28",
      "booking_hour": 17,
      "weekday": "Tuesday",
      "success": false,
      "message": "Unable to find any available Court",
      "error_type": "no_availability",
      "court_id": null,
      "court_number": null,
      "court_index": null,
      "response_time_ms": 506,
      "seconds_after_hour": 52.294,
      "booking_window": "6am",
      "thread_id": 1,
      "phase": "rapid",
      "attempt_number": 6,
      "session_age_seconds": 22.4,
      "copy_id": 2,
      "pid": 12742
    },
    {
      "timestamp": "2026-04-26T06:00:45.572559-04:00",
      "timestamp_display": "2026-04-26 06:00:45.572",
      "user": "xbai02b",
      "service": "bubble",
      "booking_date": "2026-04-28",
      "booking_hour": 15,
      "weekday": "Tuesday",
      "success": false,
      "message": "Unable to find any available Court",
      "error_type": "no_availability",
      "court_id": null,
      "court_number": null,
      "court_index": null,
      "response_time_ms": 515,
      "seconds_after_hour": 52.286,
      "booking_window": "6am",
      "thread_id": 1,
      "phase": "rapid",
      "attempt_number": 5,
      "session_age_seconds": 16.7,
      "copy_id": 2,
      "pid": 12742
    },
    {
      "timestamp": "2026-04-26T06:00:43.506679-04:00",
      "timestamp_display": "2026-04-26 06:00:43.506",
      "user": "xbai02b",
      "service": "bubble",
      "booking_date": "2026-04-28",
      "booking_hour": 14,
      "weekday": "Tuesday",
      "success": false,
      "message": "Unable to find any available Court",
      "error_type": "no_availability",
      "court_id": null,
      "court_number": null,
      "court_index": null,
      "response_time_ms": 516,
      "seconds_after_hour": 52.279,
      "booking_window": "6am",
      "thread_id": 1,
      "phase": "rapid",
      "attempt_number": 4,
      "session_age_seconds": 14.6,
      "copy_id": 2,
      "pid": 12742
    },
    {
      "timestamp": "2026-04-26T06:00:41.648982-04:00",
      "timestamp_display": "2026-04-26 06:00:41.648",
      "user": "xbai02b",
      "service": "bubble",
      "booking_date": "2026-04-28",
      "booking_hour": 17,
      "weekday": "Tuesday",
      "success": false,
      "message": "Unable to find any available Court",
      "error_type": "no_availability",
      "court_id": null,
      "court_number": null,
      "court_index": null,
      "response_time_ms": 324,
      "seconds_after_hour": 52.271,
      "booking_window": "6am",
      "thread_id": 1,
      "phase": "rapid",
      "attempt_number": 3,
      "session_age_seconds": 13.0,
      "copy_id": 2,
      "pid": 12742
    },
    {
      "timestamp": "2026-04-26T06:00:41.322553-04:00",
      "timestamp_display": "2026-04-26 06:00:41.322",
      "user": "xbai02b",
      "service": "bubble",
      "booking_date": "2026-04-28",
      "booking_hour": 15,
      "weekday": "Tuesday",
      "success": false,
      "message": "Unable to find any available Court",
      "error_type": "no_availability",
      "court_id": null,
      "court_number": null,
      "court_index": null,
      "response_time_ms": 327,
      "seconds_after_hour": 52.263,
      "booking_window": "6am",
      "thread_id": 1,
      "phase": "rapid",
      "attempt_number": 2,
      "session_age_seconds": 12.6,
      "copy_id": 2,
      "pid": 12742
    },
    {
      "timestamp": "2026-04-26T06:00:50.418660-04:00",
      "timestamp_display": "2026-04-26 06:00:50.418",
      "user": "xbai02b",
      "service": "bubble",
      "booking_date": "2026-04-28",
      "booking_hour": 14,
      "weekday": "Tuesday",
      "success": false,
      "message": "Unable to find any available Court",
      "error_type": "no_availability",
      "court_id": null,
      "court_number": null,
      "court_index": null,
      "response_time_ms": 513,
      "seconds_after_hour": 52.255,
      "booking_window": "6am",
      "thread_id": 5,
      "phase": "rapid",
      "attempt_number": 6,
      "session_age_seconds": 21.7,
      "copy_id": 2,
      "pid": 12742
    },
    {
      "timestamp": "2026-04-26T06:00:44.178545-04:00",
      "timestamp_display": "2026-04-26 06:00:44.178",
      "user": "xbai02b",
      "service": "bubble",
      "booking_date": "2026-04-28",
      "booking_hour": 17,
      "weekday": "Tuesday",
      "success": false,
      "message": "Unable to find any available Court",
      "error_type": "no_availability",
      "court_id": null,
      "court_number": null,
      "court_index": null,
      "response_time_ms": 336,
      "seconds_after_hour": 52.247,
      "booking_window": "6am",
      "thread_id": 5,
      "phase": "rapid",
      "attempt_number": 5,
      "session_age_seconds": 15.6,
      "copy_id": 2,
      "pid": 12742
    },
    {
      "timestamp": "2026-04-26T06:00:40.990658-04:00",
      "timestamp_display": "2026-04-26 06:00:40.990",
      "user": "xbai02b",
      "service": "bubble",
      "booking_date": "2026-04-28",
      "booking_hour": 15,
      "weekday": "Tuesday",
      "success": false,
      "message": "Unable to find any available Court",
      "error_type": "no_availability",
      "court_id": null,
      "court_number": null,
      "court_index": null,
      "response_time_ms": 341,
      "seconds_after_hour": 52.238,
      "booking_window": "6am",
      "thread_id": 5,
      "phase": "rapid",
      "attempt_number": 4,
      "session_age_seconds": 12.4,
      "copy_id": 2,
      "pid": 12742
    },
    {
      "timestamp": "2026-04-26T06:00:40.646474-04:00",
      "timestamp_display": "2026-04-26 06:00:40.646",
      "user": "xbai02b",
      "service": "bubble",
      "booking_date": "2026-04-28",
      "booking_hour": 14,
      "weekday": "Tuesday",
      "success": false,
      "message": "Unable to find any available Court",
      "error_type": "no_availability",
      "court_id": null,
      "court_number": null,
      "court_index": null,
      "response_time_ms": 358,
      "seconds_after_hour": 52.23,
      "booking_window": "6am",
      "thread_id": 5,
      "phase": "rapid",
      "attempt_number": 3,
      "session_age_seconds": 12.0,
      "copy_id": 2,
      "pid": 12742
    },
    {
      "timestamp": "2026-04-26T06:00:38.734784-04:00",
      "timestamp_display": "2026-04-26 06:00:38.734",
      "user": "xbai02b",
      "service": "bubble",
      "booking_date": "2026-04-28",
      "booking_hour": 17,
      "weekday": "Tuesday",
      "success": false,
      "message": "Unable to find any available Court",
      "error_type": "no_availability",
      "court_id": null,
      "court_number": null,
      "court_index": null,
      "response_time_ms": 554,
      "seconds_after_hour": 52.222,
      "booking_window": "6am",
      "thread_id": 5,
      "phase": "rapid",
      "attempt_number": 2,
      "session_age_seconds": 9.9,
      "copy_id": 2,
      "pid": 12742
    },
    {
      "timestamp": "2026-04-26T06:00:38.177814-04:00",
      "timestamp_display": "2026-04-26 06:00:38.177",
      "user": "xbai02b",
      "service": "bubble",
      "booking_date": "2026-04-28",
      "booking_hour": 15,
      "weekday": "Tuesday",
      "success": false,
      "message": "Unable to find any available Court",
      "error_type": "no_availability",
      "court_id": null,
      "court_number": null,
      "court_index": null,
      "response_time_ms": 378,
      "seconds_after_hour": 52.214,
      "booking_window": "6am",
      "thread_id": 5,
      "phase": "rapid",
      "attempt_number": 1,
      "session_age_seconds": 9.6,
      "copy_id": 2,
      "pid": 12742
    },
    {
      "timestamp": "2026-04-26T06:00:45.052653-04:00",
      "timestamp_display": "2026-04-26 06:00:45.052",
      "user": "xbai02b",
      "service": "bubble",
      "booking_date": "2026-04-28",
      "booking_hour": 14,
      "weekday": "Tuesday",
      "success": false,
      "message": "Unable to find any available Court",
      "error_type": "no_availability",
      "court_id": null,
      "court_number": null,
      "court_index": null,
      "response_time_ms": 512,
      "seconds_after_hour": 52.206,
      "booking_window": "6am",
      "thread_id": 2,
      "phase": "rapid",
      "attempt_number": 6,
      "session_age_seconds": 16.2,
      "copy_id": 2,
      "pid": 12742
    },
    {
      "timestamp": "2026-04-26T06:00:42.987238-04:00",
      "timestamp_display": "2026-04-26 06:00:42.987",
      "user": "xbai02b",
      "service": "bubble",
      "booking_date": "2026-04-28",
      "booking_hour": 17,
      "weekday": "Tuesday",
      "success": false,
      "message": "Unable to find any available Court",
      "error_type": "no_availability",
      "court_id": null,
      "court_number": null,
      "court_index": null,
      "response_time_ms": 326,
      "seconds_after_hour": 52.198,
      "booking_window": "6am",
      "thread_id": 2,
      "phase": "rapid",
      "attempt_number": 5,
      "session_age_seconds": 14.3,
      "copy_id": 2,
      "pid": 12742
    },
    {
      "timestamp": "2026-04-26T06:00:39.757274-04:00",
      "timestamp_display": "2026-04-26 06:00:39.757",
      "user": "xbai02b",
      "service": "bubble",
      "booking_date": "2026-04-28",
      "booking_hour": 15,
      "weekday": "Tuesday",
      "success": false,
      "message": "Unable to find any available Court",
      "error_type": "no_availability",
      "court_id": null,
      "court_number": null,
      "court_index": null,
      "response_time_ms": 332,
      "seconds_after_hour": 52.188,
      "booking_window": "6am",
      "thread_id": 2,
      "phase": "rapid",
      "attempt_number": 4,
      "session_age_seconds": 11.1,
      "copy_id": 2,
      "pid": 12742
    },
    {
      "timestamp": "2026-04-26T06:00:39.422120-04:00",
      "timestamp_display": "2026-04-26 06:00:39.422",
      "user": "xbai02b",
      "service": "bubble",
      "booking_date": "2026-04-28",
      "booking_hour": 14,
      "weekday": "Tuesday",
      "success": false,
      "message": "Unable to find any available Court",
      "error_type": "no_availability",
      "court_id": null,
      "court_number": null,
      "court_index": null,
      "response_time_ms": 339,
      "seconds_after_hour": 52.18,
      "booking_window": "6am",
      "thread_id": 2,
      "phase": "rapid",
      "attempt_number": 3,
      "session_age_seconds": 10.8,
      "copy_id": 2,
      "pid": 12742
    },
    {
      "timestamp": "2026-04-26T06:00:39.079864-04:00",
      "timestamp_display": "2026-04-26 06:00:39.079",
      "user": "xbai02b",
      "service": "bubble",
      "booking_date": "2026-04-28",
      "booking_hour": 17,
      "weekday": "Tuesday",
      "success": false,
      "message": "Unable to find any available Court",
      "error_type": "no_availability",
      "court_id": null,
      "court_number": null,
      "court_index": null,
      "response_time_ms": 342,
      "seconds_after_hour": 52.171,
      "booking_window": "6am",
      "thread_id": 2,
      "phase": "rapid",
      "attempt_number": 2,
      "session_age_seconds": 10.4,
      "copy_id": 2,
      "pid": 12742
    },
    {
      "timestamp": "2026-04-26T06:00:49.891796-04:00",
      "timestamp_display": "2026-04-26 06:00:49.891",
      "user": "zwang43b",
      "service": "bubble",
      "booking_date": "2026-04-28",
      "booking_hour": 17,
      "weekday": "Tuesday",
      "success": false,
      "message": "Unable to find any available Court",
      "error_type": "no_availability",
      "court_id": null,
      "court_number": null,
      "court_index": null,
      "response_time_ms": 324,
      "seconds_after_hour": 49.951,
      "booking_window": "6am",
      "thread_id": 1,
      "phase": "rapid",
      "attempt_number": 6,
      "session_age_seconds": 92.2,
      "copy_id": 3,
      "pid": 12780
    },
    {
      "timestamp": "2026-04-26T06:00:47.638194-04:00",
      "timestamp_display": "2026-04-26 06:00:47.638",
      "user": "zwang43b",
      "service": "bubble",
      "booking_date": "2026-04-28",
      "booking_hour": 14,
      "weekday": "Tuesday",
      "success": false,
      "message": "Unable to find any available Court",
      "error_type": "no_availability",
      "court_id": null,
      "court_number": null,
      "court_index": null,
      "response_time_ms": 323,
      "seconds_after_hour": 49.942,
      "booking_window": "6am",
      "thread_id": 1,
      "phase": "rapid",
      "attempt_number": 5,
      "session_age_seconds": 89.9,
      "copy_id": 3,
      "pid": 12780
    },
    {
      "timestamp": "2026-04-26T06:00:49.565013-04:00",
      "timestamp_display": "2026-04-26 06:00:49.565",
      "user": "zwang43b",
      "service": "bubble",
      "booking_date": "2026-04-28",
      "booking_hour": 14,
      "weekday": "Tuesday",
      "success": false,
      "message": "Unable to find any available Court",
      "error_type": "no_availability",
      "court_id": null,
      "court_number": null,
      "court_index": null,
      "response_time_ms": 350,
      "seconds_after_hour": 49.933,
      "booking_window": "6am",
      "thread_id": 3,
      "phase": "rapid",
      "attempt_number": 6,
      "session_age_seconds": 89.1,
      "copy_id": 3,
      "pid": 12780
    },
    {
      "timestamp": "2026-04-26T06:00:47.312816-04:00",
      "timestamp_display": "2026-04-26 06:00:47.312",
      "user": "zwang43b",
      "service": "bubble",
      "booking_date": "2026-04-28",
      "booking_hour": 15,
      "weekday": "Tuesday",
      "success": false,
      "message": "Unable to find any available Court",
      "error_type": "no_availability",
      "court_id": null,
      "court_number": null,
      "court_index": null,
      "response_time_ms": 524,
      "seconds_after_hour": 49.926,
      "booking_window": "6am",
      "thread_id": 3,
      "phase": "rapid",
      "attempt_number": 5,
      "session_age_seconds": 86.6,
      "copy_id": 3,
      "pid": 12780
    },
    {
      "timestamp": "2026-04-26T06:00:48.321365-04:00",
      "timestamp_display": "2026-04-26 06:00:48.321",
      "user": "zwang43b",
      "service": "bubble",
      "booking_date": "2026-04-28",
      "booking_hour": 17,
      "weekday": "Tuesday",
      "success": false,
      "message": "Unable to find any available Court",
      "error_type": "no_availability",
      "court_id": null,
      "court_number": null,
      "court_index": null,
      "response_time_ms": 340,
      "seconds_after_hour": 49.918,
      "booking_window": "6am",
      "thread_id": 4,
      "phase": "rapid",
      "attempt_number": 6,
      "session_age_seconds": 86.6,
      "copy_id": 3,
      "pid": 12780
    },
    {
      "timestamp": "2026-04-26T06:00:47.977928-04:00",
      "timestamp_display": "2026-04-26 06:00:47.977",
      "user": "zwang43b",
      "service": "bubble",
      "booking_date": "2026-04-28",
      "booking_hour": 15,
      "weekday": "Tuesday",
      "success": false,
      "message": "Unable to find any available Court",
      "error_type": "no_availability",
      "court_id": null,
      "court_number": null,
      "court_index": null,
      "response_time_ms": 338,
      "seconds_after_hour": 49.91,
      "booking_window": "6am",
      "thread_id": 5,
      "phase": "rapid",
      "attempt_number": 6,
      "session_age_seconds": 85.1,
      "copy_id": 3,
      "pid": 12780
    },
    {
      "timestamp": "2026-04-26T06:00:46.783981-04:00",
      "timestamp_display": "2026-04-26 06:00:46.783",
      "user": "zwang43b",
      "service": "bubble",
      "booking_date": "2026-04-28",
      "booking_hour": 15,
      "weekday": "Tuesday",
      "success": false,
      "message": "Unable to find any available Court",
      "error_type": "no_availability",
      "court_id": null,
      "court_number": null,
      "court_index": null,
      "response_time_ms": 321,
      "seconds_after_hour": 49.902,
      "booking_window": "6am",
      "thread_id": 2,
      "phase": "rapid",
      "attempt_number": 6,
      "session_age_seconds": 87.8,
      "copy_id": 3,
      "pid": 12780
    },
    {
      "timestamp": "2026-04-26T06:00:46.460268-04:00",
      "timestamp_display": "2026-04-26 06:00:46.460",
      "user": "zwang43b",
      "service": "bubble",
      "booking_date": "2026-04-28",
      "booking_hour": 17,
      "weekday": "Tuesday",
      "success": false,
      "message": "Unable to find any available Court",
      "error_type": "no_availability",
      "court_id": null,
      "court_number": null,
      "court_index": null,
      "response_time_ms": 368,
      "seconds_after_hour": 49.894,
      "booking_window": "6am",
      "thread_id": 2,
      "phase": "rapid",
      "attempt_number": 5,
      "session_age_seconds": 87.4,
      "copy_id": 3,
      "pid": 12780
    },
    {
      "timestamp": "2026-04-26T06:00:49.207201-04:00",
      "timestamp_display": "2026-04-26 06:00:49.207",
      "user": "zwang43b",
      "service": "bubble",
      "booking_date": "2026-04-28",
      "booking_hour": 15,
      "weekday": "Tuesday",
      "success": false,
      "message": "Unable to find any available Court",
      "error_type": "no_availability",
      "court_id": null,
      "court_number": null,
      "court_index": null,
      "response_time_ms": 509,
      "seconds_after_hour": 49.298,
      "booking_window": "6am",
      "thread_id": 5,
      "phase": "rapid",
      "attempt_number": 6,
      "session_age_seconds": 86.5,
      "copy_id": 2,
      "pid": 12774
    },
    {
      "timestamp": "2026-04-26T06:00:48.694373-04:00",
      "timestamp_display": "2026-04-26 06:00:48.694",
      "user": "zwang43b",
      "service": "bubble",
      "booking_date": "2026-04-28",
      "booking_hour": 17,
      "weekday": "Tuesday",
      "success": false,
      "message": "Unable to find any available Court",
      "error_type": "no_availability",
      "court_id": null,
      "court_number": null,
      "court_index": null,
      "response_time_ms": 368,
      "seconds_after_hour": 49.29,
      "booking_window": "6am",
      "thread_id": 4,
      "phase": "rapid",
      "attempt_number": 6,
      "session_age_seconds": 87.3,
      "copy_id": 2,
      "pid": 12774
    },
    {
      "timestamp": "2026-04-26T06:00:06.573685-04:00",
      "timestamp_display": "2026-04-26 06:00:06.573",
      "user": "zwang43b",
      "service": "bubble",
      "booking_date": "2026-04-28",
      "booking_hour": 15,
      "weekday": "Tuesday",
      "success": false,
      "message": "Unable to find any available Court",
      "error_type": "no_availability",
      "court_id": null,
      "court_number": null,
      "court_index": null,
      "response_time_ms": 345,
      "seconds_after_hour": 49.283,
      "booking_window": "6am",
      "thread_id": 4,
      "phase": "rapid",
      "attempt_number": 1,
      "session_age_seconds": 45.2,
      "copy_id": 2,
      "pid": 12774
    },
    {
      "timestamp": "2026-04-26T06:00:09.733139-04:00",
      "timestamp_display": "2026-04-26 06:00:09.733",
      "user": "zwang43b",
      "service": "bubble",
      "booking_date": "2026-04-28",
      "booking_hour": 14,
      "weekday": "Tuesday",
      "success": false,
      "message": "Unable to find any available Court",
      "error_type": "no_availability",
      "court_id": null,
      "court_number": null,
      "court_index": null,
      "response_time_ms": 575,
      "seconds_after_hour": 49.273,
      "booking_window": "6am",
      "thread_id": 1,
      "phase": "rapid",
      "attempt_number": 2,
      "session_age_seconds": 51.9,
      "copy_id": 2,
      "pid": 12774
    },
    {
      "timestamp": "2026-04-26T06:00:08.178880-04:00",
      "timestamp_display": "2026-04-26 06:00:08.178",
      "user": "zwang43b",
      "service": "bubble",
      "booking_date": "2026-04-28",
      "booking_hour": 14,
      "weekday": "Tuesday",
      "success": false,
      "message": "Unable to find any available Court",
      "error_type": "no_availability",
      "court_id": null,
      "court_number": null,
      "court_index": null,
      "response_time_ms": 584,
      "seconds_after_hour": 49.264,
      "booking_window": "6am",
      "thread_id": 3,
      "phase": "rapid",
      "attempt_number": 3,
      "session_age_seconds": 47.9,
      "copy_id": 2,
      "pid": 12774
    },
    {
      "timestamp": "2026-04-26T06:00:07.592449-04:00",
      "timestamp_display": "2026-04-26 06:00:07.592",
      "user": "zwang43b",
      "service": "bubble",
      "booking_date": "2026-04-28",
      "booking_hour": 15,
      "weekday": "Tuesday",
      "success": false,
      "message": "Unable to find any available Court",
      "error_type": "no_availability",
      "court_id": null,
      "court_number": null,
      "court_index": null,
      "response_time_ms": 425,
      "seconds_after_hour": 49.256,
      "booking_window": "6am",
      "thread_id": 3,
      "phase": "rapid",
      "attempt_number": 2,
      "session_age_seconds": 47.5,
      "copy_id": 2,
      "pid": 12774
    },
    {
      "timestamp": "2026-04-26T06:00:07.164992-04:00",
      "timestamp_display": "2026-04-26 06:00:07.164",
      "user": "zwang43b",
      "service": "bubble",
      "booking_date": "2026-04-28",
      "booking_hour": 17,
      "weekday": "Tuesday",
      "success": false,
      "message": "Unable to find any available Court",
      "error_type": "no_availability",
      "court_id": null,
      "court_number": null,
      "court_index": null,
      "response_time_ms": 589,
      "seconds_after_hour": 49.247,
      "booking_window": "6am",
      "thread_id": 3,
      "phase": "rapid",
      "attempt_number": 1,
      "session_age_seconds": 46.9,
      "copy_id": 2,
      "pid": 12774
    },
    {
      "timestamp": "2026-04-26T06:00:09.155333-04:00",
      "timestamp_display": "2026-04-26 06:00:09.155",
      "user": "zwang43b",
      "service": "bubble",
      "booking_date": "2026-04-28",
      "booking_hour": 14,
      "weekday": "Tuesday",
      "success": false,
      "message": "Unable to find any available Court",
      "error_type": "no_availability",
      "court_id": null,
      "court_number": null,
      "court_index": null,
      "response_time_ms": 574,
      "seconds_after_hour": 49.239,
      "booking_window": "6am",
      "thread_id": 2,
      "phase": "rapid",
      "attempt_number": 4,
      "session_age_seconds": 50.1,
      "copy_id": 2,
      "pid": 12774
    },
    {
      "timestamp": "2026-04-26T06:00:08.579345-04:00",
      "timestamp_display": "2026-04-26 06:00:08.579",
      "user": "zwang43b",
      "service": "bubble",
      "booking_date": "2026-04-28",
      "booking_hour": 15,
      "weekday": "Tuesday",
      "success": false,
      "message": "Unable to find any available Court",
      "error_type": "no_availability",
      "court_id": null,
      "court_number": null,
      "court_index": null,
      "response_time_ms": 398,
      "seconds_after_hour": 49.229,
      "booking_window": "6am",
      "thread_id": 2,
      "phase": "rapid",
      "attempt_number": 3,
      "session_age_seconds": 49.7,
      "copy_id": 2,
      "pid": 12774
    },
    {
      "timestamp": "2026-04-26T06:00:06.226371-04:00",
      "timestamp_display": "2026-04-26 06:00:06.226",
      "user": "zwang43b",
      "service": "bubble",
      "booking_date": "2026-04-28",
      "booking_hour": 17,
      "weekday": "Tuesday",
      "success": false,
      "message": "Unable to find any available Court",
      "error_type": "no_availability",
      "court_id": null,
      "court_number": null,
      "court_index": null,
      "response_time_ms": 550,
      "seconds_after_hour": 49.219,
      "booking_window": "6am",
      "thread_id": 2,
      "phase": "rapid",
      "attempt_number": 2,
      "session_age_seconds": 47.2,
      "copy_id": 2,
      "pid": 12774
    },
    {
      "timestamp": "2026-04-26T06:00:05.674015-04:00",
      "timestamp_display": "2026-04-26 06:00:05.674",
      "user": "zwang43b",
      "service": "bubble",
      "booking_date": "2026-04-28",
      "booking_hour": 14,
      "weekday": "Tuesday",
      "success": false,
      "message": "Unable to find any available Court",
      "error_type": "no_availability",
      "court_id": null,
      "court_number": null,
      "court_index": null,
      "response_time_ms": 368,
      "seconds_after_hour": 49.211,
      "booking_window": "6am",
      "thread_id": 2,
      "phase": "rapid",
      "attempt_number": 1,
      "session_age_seconds": 46.8,
      "copy_id": 2,
      "pid": 12774
    },
    {
      "timestamp": "2026-04-26T06:00:34.866147-04:00",
      "timestamp_display": "2026-04-26 06:00:34.866",
      "user": "zwang43b",
      "service": "bubble",
      "booking_date": "2026-04-28",
      "booking_hour": 14,
      "weekday": "Tuesday",
      "success": false,
      "message": "Unable to find any available Court",
      "error_type": "no_availability",
      "court_id": null,
      "court_number": null,
      "court_index": null,
      "response_time_ms": 326,
      "seconds_after_hour": 44.339,
      "booking_window": "6am",
      "thread_id": 4,
      "phase": "rapid",
      "attempt_number": 5,
      "session_age_seconds": 73.4,
      "copy_id": 1,
      "pid": 12754
    },
    {
      "timestamp": "2026-04-26T06:00:35.382972-04:00",
      "timestamp_display": "2026-04-26 06:00:35.382",
      "user": "zwang43b",
      "service": "bubble",
      "booking_date": "2026-04-28",
      "booking_hour": 17,
      "weekday": "Tuesday",
      "success": false,
      "message": "Unable to find any available Court",
      "error_type": "no_availability",
      "court_id": null,
      "court_number": null,
      "court_index": null,
      "response_time_ms": 514,
      "seconds_after_hour": 44.331,
      "booking_window": "6am",
      "thread_id": 5,
      "phase": "rapid",
      "attempt_number": 5,
      "session_age_seconds": 72.4,
      "copy_id": 1,
      "pid": 12754
    },
    {
      "timestamp": "2026-04-26T06:00:33.354224-04:00",
      "timestamp_display": "2026-04-26 06:00:33.354",
      "user": "zwang43b",
      "service": "bubble",
      "booking_date": "2026-04-28",
      "booking_hour": 14,
      "weekday": "Tuesday",
      "success": false,
      "message": "Unable to find any available Court",
      "error_type": "no_availability",
      "court_id": null,
      "court_number": null,
      "court_index": null,
      "response_time_ms": 512,
      "seconds_after_hour": 44.323,
      "booking_window": "6am",
      "thread_id": 5,
      "phase": "rapid",
      "attempt_number": 4,
      "session_age_seconds": 70.4,
      "copy_id": 1,
      "pid": 12754
    },
    {
      "timestamp": "2026-04-26T06:00:31.144988-04:00",
      "timestamp_display": "2026-04-26 06:00:31.144",
      "user": "zwang43b",
      "service": "bubble",
      "booking_date": "2026-04-28",
      "booking_hour": 15,
      "weekday": "Tuesday",
      "success": false,
      "message": "Unable to find any available Court",
      "error_type": "no_availability",
      "court_id": null,
      "court_number": null,
      "court_index": null,
      "response_time_ms": 326,
      "seconds_after_hour": 44.315,
      "booking_window": "6am",
      "thread_id": 5,
      "phase": "rapid",
      "attempt_number": 3,
      "session_age_seconds": 68.4,
      "copy_id": 1,
      "pid": 12754
    },
    {
      "timestamp": "2026-04-26T06:00:36.233767-04:00",
      "timestamp_display": "2026-04-26 06:00:36.233",
      "user": "zwang43b",
      "service": "bubble",
      "booking_date": "2026-04-28",
      "booking_hour": 15,
      "weekday": "Tuesday",
      "success": false,
      "message": "Unable to find any available Court",
      "error_type": "no_availability",
      "court_id": null,
      "court_number": null,
      "court_index": null,
      "response_time_ms": 332,
      "seconds_after_hour": 44.307,
      "booking_window": "6am",
      "thread_id": 2,
      "phase": "rapid",
      "attempt_number": 6,
      "session_age_seconds": 77.4,
      "copy_id": 1,
      "pid": 12754
    }
  ],
  "next_booking": {
    "next_window": "2026-04-27T06:00:00-04:00",
    "next_window_display": "2026-04-27 06:00 EDT",
    "target_date": "2026-04-29",
    "target_weekday": "Wednesday",
    "planned_attempts": [
      {
        "user": "xbai02b",
        "date": "2026-04-29",
        "weekday": "Wednesday",
        "hour": 14,
        "time": "14:00"
      },
      {
        "user": "xbai02b",
        "date": "2026-04-29",
        "weekday": "Wednesday",
        "hour": 15,
        "time": "15:00"
      },
      {
        "user": "xbai02b",
        "date": "2026-04-29",
        "weekday": "Wednesday",
        "hour": 17,
        "time": "17:00"
      },
      {
        "user": "zwang43b",
        "date": "2026-04-29",
        "weekday": "Wednesday",
        "hour": 15,
        "time": "15:00"
      },
      {
        "user": "zwang43b",
        "date": "2026-04-29",
        "weekday": "Wednesday",
        "hour": 14,
        "time": "14:00"
      },
      {
        "user": "zwang43b",
        "date": "2026-04-29",
        "weekday": "Wednesday",
        "hour": 17,
        "time": "17:00"
      }
    ]
  },
  "stats": {
    "total_attempts": 109581,
    "successful_attempts": 241,
    "success_rate": 0.0022
  }
}